tdigest_rs-0.1.0.dist-info/METADATA
tdigest_rs-0.1.0.dist-info/WHEEL
tdigest_rs-0.1.0.dist-info/license_files/LICENSE
tdigest_rs.libs/libgcc_s-1e52349c.so.1
tdigest_rs/__init__.py
tdigest_rs/lib.py
tdigest_rs/tdigest_rs.abi3.so
tdigest_rs-0.1.0.dist-info/RECORD
