Metadata-Version: 2.3
Name: tdigest-rs
Version: 0.1.0
Classifier: Programming Language :: Rust
Requires-Dist: hypothesis ; extra == 'dev'
Requires-Dist: joblib ; extra == 'dev'
Requires-Dist: maturin ; extra == 'dev'
Requires-Dist: pytest ; extra == 'dev'
Requires-Dist: pytest-runner ; extra == 'dev'
Requires-Dist: pytest-xdist ; extra == 'dev'
Requires-Dist: scipy ; extra == 'dev'
Requires-Dist: ruff ; extra == 'dev'
Provides-Extra: dev
License-File: LICENSE
Summary: Simple Python package to compute TDigests, implemented in Rust
Requires-Python: >=3.10
Project-URL: Repository, https://github.com/G-Research/tdigest-rs
Project-URL: Changelog, https://github.com/G-Research/tdigest-rs/releases
